MANIFEST.in
README.md
setup.py
netos_core/__init__.py
netos_core/filtersets.py
netos_core/forms.py
netos_core/models.py
netos_core/navigation.py
netos_core/tables.py
netos_core/template_content.py
netos_core/urls.py
netos_core/views.py
netos_core.egg-info/PKG-INFO
netos_core.egg-info/SOURCES.txt
netos_core.egg-info/dependency_links.txt
netos_core.egg-info/not-zip-safe
netos_core.egg-info/top_level.txt
netos_core/api/__init__.py
netos_core/api/serializers.py
netos_core/api/urls.py
netos_core/api/views.py
netos_core/migrations/0001_initial.py
netos_core/migrations/__init__.py
netos_core/static/netos_core/js/eol_report.js
netos_core/static/netos_core/js/netoshardware_list.js
netos_core/templates/netos_core/base_detail.html
netos_core/templates/netos_core/base_report.html
netos_core/templates/netos_core/eol_threshold.html
netos_core/templates/netos_core/netoseolreportdevice.html
netos_core/templates/netos_core/netoseolreportinventory.html
netos_core/templates/netos_core/netoseolreportmodule.html
netos_core/templates/netos_core/netoshardware.html
netos_core/templates/netos_core/netoshardware_report.html
netos_core/templates/netos_core/netossoftware.html
netos_core/templates/netos_core/inc/eol_report.html
netos_core/templatetags/__init__.py
netos_core/templatetags/eol_helpers.py