Metadata-Version: 2.1
Name: netos-core
Version: 0.3.4
Summary: An reconciliation plugin for NetBox
